codeyaml/__init__.py
codeyaml/plugin.py
mkdocs_codeyaml_plugin-0.0.16.dist-info/LICENSE.md
mkdocs_codeyaml_plugin-0.0.16.dist-info/METADATA
mkdocs_codeyaml_plugin-0.0.16.dist-info/WHEEL
mkdocs_codeyaml_plugin-0.0.16.dist-info/entry_points.txt
mkdocs_codeyaml_plugin-0.0.16.dist-info/top_level.txt
mkdocs_codeyaml_plugin-0.0.16.dist-info/RECORD
